pyistat/__init__.py
pyistat/errors.py
pyistat/get.py
pyistat/rate_limiter.py
pyistat/search.py
pyistat-1.1.4.dist-info/LICENSE
pyistat-1.1.4.dist-info/METADATA
pyistat-1.1.4.dist-info/WHEEL
pyistat-1.1.4.dist-info/RECORD
