Metadata-Version: 2.3
Name: pyistat
Version: 1.1.4
Summary: Pyistat is a friendly module made to easily allow anyone to use Python to search and get datasets from ISTAT APIs. There are two modules: the search module is used to find datasets and gives all the information needed to build a request URL. The get module is used to get data after helping you properly setup the dimensions (the keys, as called by ISTAT). Full documentation available on Codeberg: https://codeberg.org/Derto/pyistat
License: MPL-2.0
Author: Cosimo Di Martino
Author-email: dev.dimartino@derto.eu
Requires-Python: >=3.10
Classifier: License :: OSI Approved
Classifier: Programming Language :: Python :: 3
Classifier: Programming Language :: Python :: 3.10
Classifier: Programming Language :: Python :: 3.11
Classifier: Programming Language :: Python :: 3.12
Classifier: Programming Language :: Python :: 3.13
Requires-Dist: datetime (>=5.5,<6.0)
Requires-Dist: pandas (>=2.2.3,<3.0.0)
Requires-Dist: requests (>=2.32.3,<3.0.0)
